<?xml version="1.0" encoding="UTF-8"?>
<!DOCTYPE pdf2xml SYSTEM "pdf2xml.dtd">

<pdf2xml producer="poppler" version="0.90.1">
<page number="1" position="absolute" top="0" left="0" height="1188" width="918">
	<fontspec id="0" size="18" family="Times New Roman" color="#000000"/>
	<fontspec id="1" size="18" family="Times New Roman" color="#ffffff"/>
	<fontspec id="2" size="19" family="Times New Roman,Bold" color="#000000"/>
	<fontspec id="3" size="19" family="Times New Roman" color="#000000"/>
	<fontspec id="4" size="19" family="Times New Roman" color="#0000ff"/>
	<fontspec id="5" size="21" family="Times New Roman,Bold" color="#538dd3"/>
	<fontspec id="6" size="19" family="Symbol" color="#000000"/>
	<fontspec id="7" size="19" family="Arial" color="#000000"/>
	<fontspec id="8" size="21" family="Symbol" color="#000000"/>
	<fontspec id="9" size="21" family="Arial" color="#000000"/>
	<fontspec id="10" size="21" family="Times New Roman" color="#000000"/>
<text top="1091" left="761" width="5" height="16" font="0"> </text>
<text top="1091" left="778" width="14" height="16" font="1">1 </text>
<text top="1117" left="128" width="5" height="16" font="0"> </text>
<text top="107" left="182" width="95" height="17" font="2"><b>Full name: </b></text>
<text top="107" left="290" width="204" height="17" font="3">TRAN THI KIM  NGAN </text>
<text top="148" left="182" width="69" height="17" font="2"><b>Gender:</b></text>
<text top="148" left="251" width="67" height="17" font="3"> Female </text>
<text top="188" left="182" width="114" height="17" font="2"><b>Date of birth:</b></text>
<text top="188" left="295" width="99" height="17" font="3"> 01/02/1993 </text>
<text top="229" left="182" width="75" height="17" font="2"><b>Address:</b></text>
<text top="229" left="256" width="272" height="17" font="3"> 416-Thu Duc – Ho Chi Minh city </text>
<text top="269" left="182" width="65" height="17" font="2"><b>Mobile:</b></text>
<text top="269" left="246" width="117" height="17" font="3"> 0974 516 634 </text>
<text top="309" left="182" width="125" height="17" font="2"><b>Email address:</b></text>
<text top="309" left="307" width="5" height="17" font="3"><a href="mailto:nganttk93@gmail.com"> </a></text>
<text top="309" left="311" width="179" height="17" font="4"><a href="mailto:nganttk93@gmail.com">nganttk93@gmail.com</a></text>
<text top="309" left="491" width="5" height="17" font="3"><a href="mailto:nganttk93@gmail.com"> </a></text>
<text top="350" left="128" width="5" height="17" font="3"> </text>
<text top="400" left="128" width="298" height="19" font="5"><b>EDUCATION  BACKGROUND </b></text>
<text top="437" left="155" width="9" height="24" font="6"></text>
<text top="442" left="164" width="5" height="18" font="7"> </text>
<text top="443" left="182" width="656" height="17" font="3">Fifth  year student at  Ho Chi  Minh  City  University of Technology and Education </text>
<text top="465" left="182" width="105" height="17" font="3">(HCMUTE). </text>
<text top="501" left="155" width="9" height="24" font="6"></text>
<text top="507" left="164" width="5" height="18" font="7"> </text>
<text top="507" left="182" width="344" height="17" font="3">Field of Study: Electronic-Communication. </text>
<text top="557" left="128" width="152" height="19" font="5"><b>LANGUAGE(S) </b></text>
<text top="594" left="155" width="9" height="24" font="6"></text>
<text top="600" left="164" width="5" height="18" font="7"> </text>
<text top="600" left="182" width="176" height="17" font="3">Vietnamese (fluently) </text>
<text top="636" left="155" width="9" height="24" font="6"></text>
<text top="641" left="164" width="5" height="18" font="7"> </text>
<text top="642" left="182" width="180" height="17" font="3">English (intermediate) </text>
<text top="692" left="128" width="270" height="19" font="5"><b>PROGRAMMING ABILITY </b></text>
<text top="729" left="155" width="9" height="24" font="6"></text>
<text top="734" left="164" width="5" height="18" font="7"> </text>
<text top="735" left="182" width="656" height="17" font="3">Electronic  and  network  simulating  and  controlling  program  such  as  Matlab, </text>
<text top="757" left="182" width="288" height="17" font="3">Protues, MulitiSim, Orcad, NS2 etc. </text>
<text top="793" left="155" width="9" height="24" font="6"></text>
<text top="799" left="164" width="5" height="18" font="7"> </text>
<text top="799" left="182" width="398" height="17" font="3">Computer Languages: Visual Basic, C and Python </text>
<text top="835" left="155" width="9" height="24" font="6"></text>
<text top="840" left="164" width="5" height="18" font="7"> </text>
<text top="841" left="182" width="458" height="17" font="3">Key skills &amp; attributes: Good at self-study and team-work </text>
<text top="882" left="155" width="5" height="17" font="3"> </text>
<text top="882" left="378" width="379" height="17" font="3">Enjoy challenges and willing to learn new skills </text>
<text top="922" left="155" width="5" height="17" font="3"> </text>
<text top="922" left="378" width="250" height="17" font="3"> Be Punctual and well groomed </text>
<text top="972" left="128" width="312" height="19" font="5"><b>PROFESSIONAL EXPERIENCE </b></text>
<text top="1018" left="155" width="10" height="26" font="8"></text>
<text top="1024" left="164" width="6" height="19" font="9"> </text>
<text top="1024" left="182" width="657" height="19" font="10">03/2015–06/2015:  Be  an  intern  at  NEPTECH  center  (Dictrict  9,  Ho  Chi </text>
<text top="1048" left="182" width="95" height="19" font="10">Minh city) </text>
</page>
<page number="2" position="absolute" top="0" left="0" height="1188" width="918">
<text top="1091" left="761" width="5" height="16" font="0"> </text>
<text top="1091" left="778" width="14" height="16" font="1">2 </text>
<text top="1117" left="128" width="5" height="16" font="0"> </text>
<text top="90" left="182" width="411" height="19" font="10">Mission: Program application on kit Raspberry   </text>
<text top="141" left="182" width="267" height="19" font="10">Result: Fullfil the task on time  </text>
<text top="187" left="155" width="10" height="26" font="8"></text>
<text top="193" left="164" width="6" height="19" font="9"> </text>
<text top="194" left="182" width="138" height="19" font="10">Part-time work: </text>
<text top="245" left="182" width="7" height="19" font="10">-</text>
<text top="244" left="189" width="6" height="19" font="9"> </text>
<text top="245" left="209" width="477" height="19" font="10">2015, work at Le Loan shoes shop as a saler and cashier </text>
<text top="295" left="182" width="13" height="19" font="9">- </text>
<text top="296" left="209" width="368" height="19" font="10">2012, tutor primary student in mathematics </text>
<text top="347" left="128" width="436" height="19" font="5"><b>SPECIALIZATION AND RESEARCH AREAS </b></text>
<text top="384" left="154" width="9" height="24" font="6"></text>
<text top="390" left="163" width="5" height="18" font="7"> </text>
<text top="390" left="175" width="84" height="17" font="2"><b>Interests: </b></text>
<text top="390" left="261" width="577" height="17" font="3">Electronics  Circuits,  Electronics  Components,  Digital  Circuits,  network </text>
<text top="413" left="175" width="159" height="17" font="3">communication etc. </text>
<text top="448" left="155" width="9" height="24" font="6"></text>
<text top="454" left="164" width="5" height="18" font="7"> </text>
<text top="455" left="182" width="344" height="17" font="2"><b>Research  and  Projects(be  researching): </b></text>
<text top="455" left="529" width="309" height="17" font="3">  Apply  Zigbee  network  to  locate  the </text>
<text top="477" left="182" width="210" height="17" font="3">places that need rescuing.  </text>
<text top="518" left="128" width="196" height="19" font="5"><b>SOCIAL ACTIVITY </b></text>
<text top="555" left="155" width="9" height="24" font="6"></text>
<text top="560" left="164" width="5" height="18" font="7"> </text>
<text top="561" left="182" width="372" height="17" font="3">Participate in Green Summer program in 2013. </text>
<text top="597" left="155" width="9" height="24" font="6"></text>
<text top="602" left="164" width="5" height="18" font="7"> </text>
<text top="603" left="182" width="656" height="17" font="3">Organize  “Tu  van  tuyen  sinh”  at  Nguyen  Binh  Khiem  and  Nguyen  Thong  high </text>
<text top="625" left="182" width="56" height="17" font="3">school </text>
<text top="661" left="155" width="9" height="24" font="6"></text>
<text top="667" left="164" width="5" height="18" font="7"> </text>
<text top="667" left="182" width="327" height="17" font="3"> Participate in “Tiep Suc Mua Thi 2011”. </text>
<text top="708" left="182" width="5" height="17" font="3"> </text>
<text top="749" left="128" width="146" height="19" font="5"><b>REFERENCES </b></text>
<text top="790" left="128" width="331" height="17" font="3">Will be made available upon your request </text>
<text top="830" left="128" width="5" height="17" font="3"> </text>
</page>
</pdf2xml>
